{
"123456": {
   "password": "$2y$12$Jqj/GD6TALHvJUZ.Kp8z/.9orKFGCHHz0Jce8o48Ho.Ucz69B4dlK",
   "devices": ["REDMINOTE9PRO4C097BE57F979E83"],
   "expiry": "31-10-2024 12:00 PM"
},
   "ZFC123456": {
   "password": "$2y$12$ahxfYTI1uZy3hVCJ445Ivepknp.nf7PYvFhTqJJJ6YDlB/vJ352ay",
   "devices": ["REDMINOTE9PRO4C097BE57F979E83"],
   "expiry": "31-10-2024 12:00 PM"
},
   "kalea": {
   "password": "$2y$12$QaWSwOtGA.Pn2dOveO2etefABfvuyuv4WW/6BHu.Bxz9tdTEOBd.i",
   "devices": ["CPH180399950238"],
   "expiry": "30-11-2024 12:00 PM"
},
  "andrewtea": {
   "password": "$2y$12$e9g7sigslRYVdRYATPMnOucSuYT.2sKwn/BXYPaeZ/uWXxGl3dU3m",
   "devices": ["23021RAA2Y76CBB3D8B7A970DA"],
   "expiry": "30-11-2024 12:00 PM"
},
}
